emepy/__init__.py
emepy/_tidy3d.py
emepy/ann.py
emepy/eme.py
emepy/fd.py
emepy/geometries.py
emepy/lumerical.py
emepy/materials.py
emepy/mode.py
emepy/models.py
emepy/monitors.py
emepy/optimization.py
emepy/source.py
emepy/tools.py
emepy-1.2.2.dist-info/LICENSE
emepy-1.2.2.dist-info/METADATA
emepy-1.2.2.dist-info/WHEEL
emepy-1.2.2.dist-info/top_level.txt
emepy-1.2.2.dist-info/RECORD
